llm_tools_hub/__init__.py
llm_tools_hub/core.py
llm_tools_hub-1.2.0.dist-info/METADATA
llm_tools_hub-1.2.0.dist-info/WHEEL
llm_tools_hub-1.2.0.dist-info/top_level.txt
llm_tools_hub-1.2.0.dist-info/RECORD
