Metadata-Version: 2.2
Name: llm-tools-hub
Version: 1.2.0
Summary: Instant integration of external tools into LLM applications via automatic function calling.
Home-page: https://github.com/ronivaldo/llm-tools-hub
Author: Ronivaldo Sampaio
Author-email: ronivaldo@gmail.com
Classifier: Programming Language :: Python :: 3
Classifier: License :: OSI Approved :: MIT License
Classifier: Operating System :: OS Independent
Requires-Python: >=3.7
Requires-Dist: openai==0.28
Dynamic: author
Dynamic: author-email
Dynamic: classifier
Dynamic: description
Dynamic: description-content-type
Dynamic: home-page
Dynamic: requires-dist
Dynamic: requires-python
Dynamic: summary
